spire/__init__.py
spire/api.py
spire/broodusers.py
spire/data.py
spire/db.py
spire/es.py
spire/indices.py
spire/middleware.py
spire/version.py
spire/github/__init__.py
spire/github/actions.py
spire/github/api.py
spire/github/calls.py
spire/github/checks.py
spire/github/cli.py
spire/github/commands.py
spire/github/data.py
spire/github/events.py
spire/github/handlers.py
spire/github/models.py
spire/github/version.py
spire/github/upgrades/__init__.py
spire/github/upgrades/broodauth.py
spire/go/__init__.py
spire/go/actions.py
spire/go/api.py
spire/go/cli.py
spire/go/data.py
spire/go/models.py
spire/go/version.py
spire/humbug/__init__.py
spire/humbug/actions.py
spire/humbug/api.py
spire/humbug/cli.py
spire/humbug/data.py
spire/humbug/models.py
spire/humbug/version.py
spire/journal/__init__.py
spire/journal/actions.py
spire/journal/api.py
spire/journal/cli.py
spire/journal/data.py
spire/journal/models.py
spire/journal/search.py
spire/journal/version.py
spire/preferences/__init__.py
spire/preferences/actions.py
spire/preferences/api.py
spire/preferences/data.py
spire/preferences/errors.py
spire/preferences/models.py
spire/preferences/version.py
spire/public/__init__.py
spire/public/actions.py
spire/public/api.py
spire/public/cli.py
spire/public/models.py
spire/public/version.py
spire/slack/__init__.py
spire/slack/admin.py
spire/slack/api.py
spire/slack/commands.py
spire/slack/data.py
spire/slack/handlers.py
spire/slack/indices.py
spire/slack/installations.py
spire/slack/interactions.py
spire/slack/models.py
spire/slack/parse.py
spire/slack/reactions.py
spire/slack/version.py
spire/slack/upgrades/__init__.py
spire/slack/upgrades/auth_0.py
spire/slack/upgrades/auto.py
spire/slack/upgrades/scopes.py
spire/slack/upgrades/version_1.py
spire/slack/upgrades/version_2.py
spire/slack/upgrades/version_3.py
spire/utils/__init__.py
spire/utils/bugoutargparse.py
spire/utils/confparse.py
spire/utils/settings.py
bugout_spire-0.4.2.dist-info/LICENSE
bugout_spire-0.4.2.dist-info/METADATA
bugout_spire-0.4.2.dist-info/WHEEL
bugout_spire-0.4.2.dist-info/entry_points.txt
bugout_spire-0.4.2.dist-info/top_level.txt
bugout_spire-0.4.2.dist-info/RECORD
