Metadata-Version: 2.1
Name: bugout-spire
Version: 0.4.2
Summary: Spire: Bugout custom knowledge base
Home-page: https://github.com/bugout-dev/spire
Author: Bugout.dev
Author-email: engineering@bugout.dev
License: UNKNOWN
Platform: all
Classifier: Development Status :: 3 - Alpha
Classifier: Intended Audience :: Developers
Classifier: Natural Language :: English
Classifier: Programming Language :: Python
Classifier: License :: OSI Approved :: Apache Software License
Classifier: Topic :: Software Development :: Libraries
Requires-Python: >=3.6
Requires-Dist: aiofiles
Requires-Dist: aiohttp
Requires-Dist: appdirs
Requires-Dist: attrs
Requires-Dist: boto3 (>=1.20.2)
Requires-Dist: bugout (>=0.1.19)
Requires-Dist: bugout-brood (>=0.2.2)
Requires-Dist: bugout-locust (>=0.2.8)
Requires-Dist: cached-property
Requires-Dist: chardet
Requires-Dist: cryptography
Requires-Dist: docutils
Requires-Dist: elasticsearch (==7.8.1)
Requires-Dist: fastapi (>=0.75.0)
Requires-Dist: httptools
Requires-Dist: multidict
Requires-Dist: protobuf (==3.19.1)
Requires-Dist: psycopg2-binary (>=2.9.1)
Requires-Dist: pydantic
Requires-Dist: PyJWT (==1.7.1)
Requires-Dist: redis
Requires-Dist: requests
Requires-Dist: sqlalchemy (>=1.4.26)
Requires-Dist: toml
Requires-Dist: typed-ast
Requires-Dist: uvicorn (>=0.17.6)
Requires-Dist: uvloop
Requires-Dist: websockets
Requires-Dist: yarl
Provides-Extra: dev
Requires-Dist: alembic ; extra == 'dev'
Requires-Dist: black ; extra == 'dev'
Requires-Dist: isort ; extra == 'dev'
Requires-Dist: mypy ; extra == 'dev'
Requires-Dist: types-redis ; extra == 'dev'
Requires-Dist: types-requests ; extra == 'dev'
Requires-Dist: types-python-dateutil ; extra == 'dev'
Requires-Dist: types-toml ; extra == 'dev'
Provides-Extra: distribute
Requires-Dist: setuptools ; extra == 'distribute'
Requires-Dist: twine ; extra == 'distribute'
Requires-Dist: wheel ; extra == 'distribute'
